gojot/__init__.py
gojot/cli.py
gojot/gojot.py
gojot-3.0.3.dist-info/DESCRIPTION.rst
gojot-3.0.3.dist-info/METADATA
gojot-3.0.3.dist-info/RECORD
gojot-3.0.3.dist-info/WHEEL
gojot-3.0.3.dist-info/entry_points.txt
gojot-3.0.3.dist-info/metadata.json
gojot-3.0.3.dist-info/top_level.txt
