Metadata-Version: 2.0
Name: gojot
Version: 3.0.3
Summary: A command-line journal that is distributed and encrypted, making it easy to jot notes.
Home-page: https://github.com/schollz/gojot
Author: Zack Scholl
Author-email: zack.scholl@gmail.com
License: MIT license
Keywords: gojot
Platform: UNKNOWN
Classifier: Development Status :: 2 - Pre-Alpha
Classifier: Intended Audience :: Developers
Classifier: License :: OSI Approved :: MIT License
Classifier: Natural Language :: English
Classifier: Programming Language :: Python :: 3.3
Classifier: Programming Language :: Python :: 3.4
Classifier: Programming Language :: Python :: 3.5
Requires-Dist: Click (>=6.0)
Requires-Dist: hashids
Requires-Dist: humanize
Requires-Dist: pick
Requires-Dist: ruamel.yaml
Requires-Dist: termcolor
Requires-Dist: tqdm
